qclatticeh/README.md
qclatticeh/__init__.py
qclatticeh/old__init__.py
qclatticeh/circuits/Ansaetze.py
qclatticeh/circuits/__init__.py
qclatticeh/hamiltonian/Hamiltonian_QED_oprt.py
qclatticeh/hamiltonian/Hamiltonian_QED_sym.py
qclatticeh/hamiltonian/__init__.py
qclatticeh/lattice/HC_Lattice.py
qclatticeh/lattice/__init__.py
qclatticeh-0.1.0.dist-info/METADATA
qclatticeh-0.1.0.dist-info/WHEEL
qclatticeh-0.1.0.dist-info/licenses/LICENSE
qclatticeh-0.1.0.dist-info/RECORD
