Metadata-Version: 2.4
Name: qclatticeh
Version: 0.1.0
Summary: Lattice QED Hamiltonian for Quantum Computing
Project-URL: Documentation, https://github.com/ariannacrippa/QC_lattice_H#readme
Project-URL: Issues, https://github.com/ariannacrippa/QC_lattice_H/issues
Project-URL: Source, https://github.com/ariannacrippa/QC_lattice_H/
Author-email: Arianna Crippa <cripparianna@gmail.com>, Emil Rosanowski <rosanowski@hiskp.uni-bonn.de>, Paulo Itaborai <itaborapuy@gmail.com>
License-Expression: MIT
License-File: LICENSE
Classifier: Development Status :: 4 - Beta
Classifier: Programming Language :: Python
Classifier: Programming Language :: Python :: 3.10
Classifier: Programming Language :: Python :: 3.11
Classifier: Programming Language :: Python :: 3.12
Requires-Python: >=3.10
Requires-Dist: iteration-utilities
Requires-Dist: matplotlib
Requires-Dist: networkx
Requires-Dist: numpy
Requires-Dist: sympy
Provides-Extra: all
Requires-Dist: qiskit; extra == 'all'
Requires-Dist: scipy; extra == 'all'
Provides-Extra: ed
Requires-Dist: scipy; extra == 'ed'
Provides-Extra: qc
Requires-Dist: qiskit; extra == 'qc'
